LFPWM/LFPWM_main.py
LFPWM/__init__.py
LFPWM/home.py
LFPWM/query.py
LFPWM/sql_db.py
LFPWM/test.py
LFPWM/users.py
LFPWM-1.1.0.dist-info/LICENSE
LFPWM-1.1.0.dist-info/METADATA
LFPWM-1.1.0.dist-info/WHEEL
LFPWM-1.1.0.dist-info/top_level.txt
LFPWM-1.1.0.dist-info/RECORD
