Metadata-Version: 2.1
Name: LFPWM
Version: 1.1.0
Summary: LamaForge Encrypted Password Manager/User Auth
Author: LamaForge (Jadon Lama)
Author-email: <lamaforgecode@gmail.com>
Keywords: python,encryption,data,password manager,user auth
Classifier: Development Status :: 3 - Alpha
Classifier: Intended Audience :: Developers
Classifier: Programming Language :: Python :: 3
Classifier: Operating System :: Unix
Classifier: Operating System :: MacOS :: MacOS X
Classifier: Operating System :: Microsoft :: Windows
License-File: LICENSE
Requires-Dist: bcrypt
Requires-Dist: cryptography
